flask_oidc/__init__.py
flask_oidc/discovery.py
flask_oidc/registration.py
flask_oidc/registration_util.py
flask_oidc2-1.5.0.dist-info/LICENSE.txt
flask_oidc2-1.5.0.dist-info/METADATA
flask_oidc2-1.5.0.dist-info/WHEEL
flask_oidc2-1.5.0.dist-info/entry_points.txt
flask_oidc2-1.5.0.dist-info/top_level.txt
flask_oidc2-1.5.0.dist-info/RECORD
