Metadata-Version: 2.1
Name: flask-oidc2
Version: 1.5.0
Summary: OpenID Connect extension for Flask
Home-page: https://github.com/vishnu667/flask-oidc2
Author: Vishnu Prasad, Patrick Uiterwijk
Author-email: vishnu667@gmail.com
License: UNKNOWN
Project-URL: Bug Tracker, https://github.com/vishnu667/flask-oidc2/issues
Project-URL: Documentation, https://flask-oidc2.readthedocs.io/
Project-URL: Source Code, https://github.com/vishnu667/flask-oidc2/
Platform: UNKNOWN
Classifier: Environment :: Web Environment
Classifier: Framework :: Flask
Classifier: Intended Audience :: Developers
Classifier: License :: OSI Approved :: BSD License
Classifier: Operating System :: OS Independent
Classifier: Programming Language :: Python
Classifier: Programming Language :: Python :: 3
Classifier: Programming Language :: Python :: 3.6
Classifier: Programming Language :: Python :: 3.7
Classifier: Programming Language :: Python :: 3.8
Classifier: Topic :: Internet :: WWW/HTTP :: Dynamic Content
Classifier: Topic :: Software Development :: Libraries :: Python Modules
Requires-Dist: flask
Requires-Dist: itsdangerous
Requires-Dist: oauth2client
Requires-Dist: six
